spa_deploy/__init__.py
spa_deploy/py.typed
spa_deploy/_jsii/__init__.py
spa_deploy/_jsii/cdk-spa-deploy@1.104.1.jsii.tgz
cdk_spa_deploy-1.104.1.dist-info/LICENSE
cdk_spa_deploy-1.104.1.dist-info/METADATA
cdk_spa_deploy-1.104.1.dist-info/WHEEL
cdk_spa_deploy-1.104.1.dist-info/top_level.txt
cdk_spa_deploy-1.104.1.dist-info/RECORD
