Metadata-Version: 2.1
Name: cdk-spa-deploy
Version: 1.104.1
Summary: This is an AWS CDK Construct to make deploying a single page website (Angular/React/Vue) to AWS S3 behind SSL/Cloudfront as easy as 5 lines of code.
Home-page: https://github.com/nideveloper/CDK-SPA-Deploy.git
Author: hi@cdkpatterns.com
License: MIT
Project-URL: Source, https://github.com/nideveloper/CDK-SPA-Deploy.git
Platform: UNKNOWN
Classifier: Intended Audience :: Developers
Classifier: Operating System :: OS Independent
Classifier: Programming Language :: JavaScript
Classifier: Programming Language :: Python :: 3 :: Only
Classifier: Programming Language :: Python :: 3.6
Classifier: Programming Language :: Python :: 3.7
Classifier: Programming Language :: Python :: 3.8
Classifier: Programming Language :: Python :: 3.9
Classifier: Typing :: Typed
Classifier: License :: OSI Approved
Requires-Python: >=3.6
Requires-Dist: aws-cdk.aws-certificatemanager (<2.0.0,>=1.103.0)
Requires-Dist: aws-cdk.aws-cloudfront (<2.0.0,>=1.103.0)
Requires-Dist: aws-cdk.aws-iam (<2.0.0,>=1.103.0)
Requires-Dist: aws-cdk.aws-route53-patterns (<2.0.0,>=1.103.0)
Requires-Dist: aws-cdk.aws-route53-targets (<2.0.0,>=1.103.0)
Requires-Dist: aws-cdk.aws-route53 (<2.0.0,>=1.103.0)
Requires-Dist: aws-cdk.aws-s3-deployment (<2.0.0,>=1.103.0)
Requires-Dist: aws-cdk.aws-s3 (<2.0.0,>=1.103.0)
Requires-Dist: aws-cdk.core (<2.0.0,>=1.103.0)
Requires-Dist: constructs (<4.0.0,>=3.3.75)
Requires-Dist: jsii (<2.0.0,>=1.29.0)
Requires-Dist: publication (>=0.0.3)
